pytochnog3/__init__.py
pytochnog3/pytochnog3.py
pytochnog3-0.0.2.dist-info/LICENSE
pytochnog3-0.0.2.dist-info/METADATA
pytochnog3-0.0.2.dist-info/WHEEL
pytochnog3-0.0.2.dist-info/top_level.txt
pytochnog3-0.0.2.dist-info/RECORD
